neofetch_win/__init__.py
neofetch_win/__main__.py
neofetch_win/art.py
neofetch_win/neofetch.py
neofetch_win-1.4.4.dist-info/licenses/LICENSE
neofetch_win-1.4.4.dist-info/METADATA
neofetch_win-1.4.4.dist-info/WHEEL
neofetch_win-1.4.4.dist-info/entry_points.txt
neofetch_win-1.4.4.dist-info/top_level.txt
neofetch_win-1.4.4.dist-info/RECORD
