Metadata-Version: 2.4
Name: neofetch-win
Version: 1.4.4
Summary: neofetch, but for Windows
Author-email: AlexFlipnote <root@alexflipnote.dev>
License: MIT
Project-URL: Homepage, https://github.com/AlexFlipnote/neofetch-win
Project-URL: Repository, https://github.com/AlexFlipnote/neofetch-win
Keywords: python,windows,ascii,pip,neofetch
Requires-Python: >=3.11.0
License-File: LICENSE
Requires-Dist: psutil
Requires-Dist: wmi
Provides-Extra: dev
Requires-Dist: pyright; extra == "dev"
Requires-Dist: ruff; extra == "dev"
Requires-Dist: toml; extra == "dev"
Dynamic: license-file
